pyraptorq/__init__.py
pyraptorq/decoder.py
pyraptorq/encoder.py
pyraptorq/engine.py
pyraptorq/raptorq_cpp_engine.py
pyraptorq/distlib/darwin/libpyraptorq.arm64.dylib
pyraptorq/distlib/darwin/libpyraptorq.x86_64.dylib
pyraptorq/distlib/linux/libpyraptorq.aarch64.so
pyraptorq/distlib/linux/libpyraptorq.x86_64.so
pyraptorq/distlib/windows/libpyraptorq.x86_64.dll
pyraptorq-0.1.7.dist-info/METADATA
pyraptorq-0.1.7.dist-info/WHEEL
pyraptorq-0.1.7.dist-info/top_level.txt
pyraptorq-0.1.7.dist-info/RECORD
